code2seq/__init__.py
code2seq/code2class_wrapper.py
code2seq/code2seq_wrapper.py
code2seq/typed_code2seq_wrapper.py
code2seq/data/__init__.py
code2seq/data/path_context.py
code2seq/data/path_context_data_module.py
code2seq/data/path_context_dataset.py
code2seq/data/typed_path_context_data_module.py
code2seq/data/typed_path_context_dataset.py
code2seq/data/vocabulary.py
code2seq/model/__init__.py
code2seq/model/code2class.py
code2seq/model/code2seq.py
code2seq/model/typed_code2seq.py
code2seq/model/modules/__init__.py
code2seq/model/modules/path_encoder.py
code2seq/model/modules/typed_path_encoder.py
code2seq/utils/__init__.py
code2seq/utils/common.py
code2seq/utils/optimization.py
code2seq/utils/test.py
code2seq/utils/train.py
code2seq-1.2.0.dist-info/LICENSE
code2seq-1.2.0.dist-info/METADATA
code2seq-1.2.0.dist-info/WHEEL
code2seq-1.2.0.dist-info/top_level.txt
code2seq-1.2.0.dist-info/RECORD
