Metadata-Version: 2.1
Name: code2seq
Version: 1.2.0
Summary: Set of pytorch modules and utils to train code2seq model
Home-page: https://github.com/JetBrains-Research/code2seq
Author: Egor Spirin
Author-email: spirin.egor@gmail.com
License: MIT
Download-URL: https://pypi.org/project/code2seq/
Keywords: code2seq,pytorch,pytorch-lightning,ml4code,ml4se
Platform: UNKNOWN
License-File: LICENSE
Requires-Dist: torch (>=1.10.0)
Requires-Dist: pytorch-lightning (~=1.5.0)
Requires-Dist: wandb (~=0.12.0)
Requires-Dist: omegaconf (~=2.1.1)
Requires-Dist: commode-utils (>=0.4.0)
